devtools/run_linting.py
devtools/update_copyright.py
devtools/docs/check_api_docs.py
devtools/docs/make_table.py
devtools/docs/mpl_object.py
docs/_build/html/_downloads/3b35b24effc1e0d697563ad0134057a7/retis.py
docs/_build/html/_downloads/f765dbb27e6e2b499f70971a58185fc5/retis_movie.py
docs/_build/html/_static/api/box_example.py
docs/_build/html/_static/api/box_example_create.py
docs/_build/html/_static/api/lattice_example.py
docs/_build/html/_static/engine-examples/leapfrog.py
docs/_build/html/_static/engine-examples/newexternal.py
docs/_build/html/_static/engine-examples/openmm_sim.py
docs/_build/html/_static/examples/examples_mc.py
docs/_build/html/_static/examples/harmonic1d.py
docs/_build/html/_static/examples/md.py
docs/_build/html/_static/examples/orderintro.py
docs/_build/html/_static/examples/orderintro2.py
docs/_build/html/_static/examples/pathintro.py
docs/_build/html/_static/examples/simulationintro.py
docs/_build/html/_static/examples/extending-example/engine/setup.py
docs/_build/html/_static/examples/extending-example/engine/vvintegratorc.py
docs/_build/html/_static/examples/extending-example/engine/vvintegratorf.py
docs/_build/html/_static/examples/extending-example/potential/ljpotentialc.py
docs/_build/html/_static/examples/extending-example/potential/ljpotentialfp.py
docs/_build/html/_static/examples/extending-example/potential/setup.py
docs/_build/html/_static/examples/extending-example/potentialfb/ljpotentialc.py
docs/_build/html/_static/examples/extending-example/potentialfb/ljpotentialf.py
docs/_build/html/_static/examples/extending-example/potentialfb/md_forward_backward_ext.py
docs/_build/html/_static/examples/extending-example/potentialfb/setup.py
docs/_build/html/_static/examples/gromacs-hydrate/orderp.py
docs/_build/html/_static/examples/pso-example/ackley.py
docs/_build/html/_static/examples/pso-example/pso_run.py
docs/_build/html/_static/examples/pso-example/psoengine.py
docs/_build/html/_static/examples/retis2d-hysteresis/order-x.py
pyretis-2.5.0.dist-info/LICENSE
pyretis-2.5.0.dist-info/METADATA
pyretis-2.5.0.dist-info/WHEEL
pyretis-2.5.0.dist-info/entry_points.txt
pyretis-2.5.0.dist-info/top_level.txt
pyretis-2.5.0.dist-info/RECORD
